imppy3d/__init__.py
imppy3d/bounding_box.py
imppy3d/cv_driver_functions.py
imppy3d/cv_interactive_processing.py
imppy3d/cv_processing_wrappers.py
imppy3d/im3_processing.c
imppy3d/im3_processing.cp310-win_amd64.pyd
imppy3d/im3_processing.pyx
imppy3d/import_export.py
imppy3d/plt_wrappers.py
imppy3d/ski_driver_functions.py
imppy3d/ski_interactive_processing.py
imppy3d/ski_processing_wrappers.py
imppy3d/volume_image_processing.py
imppy3d/vtk_api.py
imppy3d/cython/__init__.py
imppy3d/cython/cython_build_setup.py
imppy3d/cython/im3_processing.c
imppy3d-1.2.0.dist-info/LICENSE.txt
imppy3d-1.2.0.dist-info/METADATA
imppy3d-1.2.0.dist-info/WHEEL
imppy3d-1.2.0.dist-info/top_level.txt
imppy3d-1.2.0.dist-info/RECORD
