Metadata-Version: 2.1
Name: imppy3d
Version: 1.2.0
Summary: IMPPY3D: A library for processing 3D image stacks
Home-page: https://github.com/usnistgov/imppy3d/
Author: Newell Moser
Author-email: newell.moser@nist.gov
Classifier: Programming Language :: Python :: 3
Classifier: Programming Language :: Cython
Classifier: License :: OSI Approved :: MIT License
Classifier: Operating System :: MacOS
Classifier: Operating System :: POSIX :: Linux
Classifier: Operating System :: Microsoft :: Windows
Requires-Python: ==3.10.*
License-File: LICENSE.txt
Requires-Dist: numpy==1.26.*
Requires-Dist: scipy==1.11.*
Requires-Dist: matplotlib==3.8.*
Requires-Dist: scikit-image==0.20.*
Requires-Dist: opencv-python==4.6.*
Requires-Dist: vtk<=9.3,>9.1
Requires-Dist: pyvista==0.34.*
Requires-Dist: meshio==5.3.*
Requires-Dist: imagecodecs>=2022.7
Requires-Dist: tifffile>=2022
